signhost/__init__.py
signhost/__main__.py
signhost/client/__init__.py
signhost/client/asyncio.py
signhost/client/base.py
signhost/client/default.py
signhost/client/errors.py
signhost/client/utils.py
signhost/models/__init__.py
signhost/models/enums.py
signhost/models/forms.py
signhost/models/generated.py
signhost/models/location.py
signhost/models/verifications.py
signhost/py.typed
signhost_api_python_client-0.3.0.dist-info/LICENSE
signhost_api_python_client-0.3.0.dist-info/METADATA
signhost_api_python_client-0.3.0.dist-info/WHEEL
signhost_api_python_client-0.3.0.dist-info/entry_points.txt
signhost_api_python_client-0.3.0.dist-info/RECORD
