Metadata-Version: 2.1
Name: signhost-api-python-client
Version: 0.3.0
Summary: Signhost Api Python Client
Home-page: https://github.com/foarsitter/signhost-api-python-client
License: MIT
Author: Jelmer Draaijer
Author-email: info@jelmert.nl
Requires-Python: >=3.7,<4.0
Classifier: Development Status :: 4 - Beta
Classifier: License :: OSI Approved :: MIT License
Classifier: Programming Language :: Python :: 3
Classifier: Programming Language :: Python :: 3.7
Classifier: Programming Language :: Python :: 3.8
Classifier: Programming Language :: Python :: 3.9
Classifier: Programming Language :: Python :: 3.10
Classifier: Programming Language :: Python :: 3.11
Requires-Dist: attrs (>=23.1.0,<24.0.0)
Requires-Dist: click (>=8.0.1)
Requires-Dist: httpx (>=0.24.1,<0.25.0)
Requires-Dist: pydantic (>=2.0.1)
Project-URL: Changelog, https://github.com/foarsitter/signhost-api-python-client/releases
Project-URL: Documentation, https://signhost-api-python-client.readthedocs.io
Project-URL: Repository, https://github.com/foarsitter/signhost-api-python-client
